CaraUpload.txt
LICENSE
MANIFEST.in
README.md
requirements.txt
setup.py
umkt_service_utils/__init__.py
umkt_service_utils/admin.py
umkt_service_utils/apps.py
umkt_service_utils/auth_middleware.py
umkt_service_utils/models.py
umkt_service_utils/pagination.py
umkt_service_utils/permissions.py
umkt_service_utils/serializers.py
umkt_service_utils/services.py
umkt_service_utils/tests.py
umkt_service_utils/umkt_jwt_middleware.py
umkt_service_utils/urls.py
umkt_service_utils/views.py
umkt_utility_v2.egg-info/PKG-INFO
umkt_utility_v2.egg-info/SOURCES.txt
umkt_utility_v2.egg-info/dependency_links.txt
umkt_utility_v2.egg-info/requires.txt
umkt_utility_v2.egg-info/top_level.txt