Metadata-Version: 2.1
Name: umkt-utility-v2
Version: 0.1
Summary: My package description
Home-page: https://git.umkt.ac.id/services/umkt-service-utility
Author: 2ez4ad1
Author-email: mra441@umkt.ac.id
License-File: LICENSE
Requires-Dist: django
Requires-Dist: djangorestframework
Requires-Dist: requests
Requires-Dist: PyJWT
Requires-Dist: python-decouple
